LICENSE
README.md
ntml/__init__.py
ntml/const.py
ntml/ntml_parser.py
ntml/ntmlc.py
ntml/setup.py
ntml/tran.py
ntml.egg-info/PKG-INFO
ntml.egg-info/SOURCES.txt
ntml.egg-info/dependency_links.txt
ntml.egg-info/not-zip-safe
ntml.egg-info/requires.txt
ntml.egg-info/top_level.txt